[
  {
    "slug": "agen",
    "name": "Déménagement"
  },
  {
    "slug": "ajaccio",
    "name": "professionnel à Agen"
  },
  {
    "slug": "albi",
    "name": "Déménagement"
  },
  {
    "slug": "alencon",
    "name": "Déménagement"
  },
  {
    "slug": "amiens",
    "name": "Déménagement"
  },
  {
    "slug": "angers",
    "name": "Déménagement"
  },
  {
    "slug": "angouleme",
    "name": "Déménagement"
  },
  {
    "slug": "annecy",
    "name": "Déménagement"
  },
  {
    "slug": "arras",
    "name": "Déménagement"
  },
  {
    "slug": "auch",
    "name": "Déménagement"
  },
  {
    "slug": "aurillac",
    "name": "Déménagement"
  },
  {
    "slug": "auxerre",
    "name": "Déménagement"
  },
  {
    "slug": "avignon",
    "name": "Déménagement"
  },
  {
    "slug": "bar-le-duc",
    "name": "Déménagement"
  },
  {
    "slug": "bastia",
    "name": "professionnel à Agen"
  },
  {
    "slug": "beauvais",
    "name": "Déménagement"
  },
  {
    "slug": "belfort",
    "name": "Déménagement"
  },
  {
    "slug": "besancon",
    "name": "Déménagement"
  },
  {
    "slug": "blois",
    "name": "Déménagement"
  },
  {
    "slug": "bobigny",
    "name": "Déménagement"
  },
  {
    "slug": "bordeaux",
    "name": "Déménagement"
  },
  {
    "slug": "bourg-en-bresse",
    "name": "Déménagement"
  },
  {
    "slug": "bourges",
    "name": "Déménagement"
  },
  {
    "slug": "brest",
    "name": "professionnel à Agen"
  },
  {
    "slug": "caen",
    "name": "Déménagement"
  },
  {
    "slug": "cahors",
    "name": "Déménagement"
  },
  {
    "slug": "carcassonne",
    "name": "Déménagement"
  },
  {
    "slug": "cergy",
    "name": "Déménagement"
  },
  {
    "slug": "chambery",
    "name": "Déménagement"
  },
  {
    "slug": "charleville-mezieres",
    "name": "Déménagement"
  },
  {
    "slug": "chartres",
    "name": "Déménagement"
  },
  {
    "slug": "chateauroux",
    "name": "Déménagement"
  },
  {
    "slug": "chaumont",
    "name": "Déménagement"
  },
  {
    "slug": "clermont-ferrand",
    "name": "Déménagement"
  },
  {
    "slug": "creteil",
    "name": "Déménagement"
  },
  {
    "slug": "digne-les-bains",
    "name": "Déménagement"
  },
  {
    "slug": "dijon",
    "name": "Déménagement"
  },
  {
    "slug": "epinal",
    "name": "Déménagement"
  },
  {
    "slug": "evreux",
    "name": "Déménagement"
  },
  {
    "slug": "evry",
    "name": "Déménagement"
  },
  {
    "slug": "foix",
    "name": "Déménagement"
  },
  {
    "slug": "gap",
    "name": "Déménagement"
  },
  {
    "slug": "grenoble",
    "name": "Déménagement"
  },
  {
    "slug": "gueret",
    "name": "Déménagement"
  },
  {
    "slug": "la-roche-sur-yon",
    "name": "Déménagement"
  },
  {
    "slug": "la-rochelle",
    "name": "Déménagement"
  },
  {
    "slug": "laon",
    "name": "Déménagement"
  },
  {
    "slug": "laval",
    "name": "Déménagement"
  },
  {
    "slug": "le-mans",
    "name": "Déménagement"
  },
  {
    "slug": "le-puy-en-velay",
    "name": "Déménagement"
  },
  {
    "slug": "lille",
    "name": "Déménagement"
  },
  {
    "slug": "limoges",
    "name": "Déménagement"
  },
  {
    "slug": "lons-le-saunier",
    "name": "Déménagement"
  },
  {
    "slug": "lyon",
    "name": "Déménagement"
  },
  {
    "slug": "macon",
    "name": "Déménagement"
  },
  {
    "slug": "marseille",
    "name": "Déménagement"
  },
  {
    "slug": "melun",
    "name": "Déménagement"
  },
  {
    "slug": "mende",
    "name": "Déménagement"
  },
  {
    "slug": "metz",
    "name": "Déménagement"
  },
  {
    "slug": "mont-de-marsan",
    "name": "Déménagement"
  },
  {
    "slug": "montauban",
    "name": "Déménagement"
  },
  {
    "slug": "montpellier",
    "name": "Déménagement"
  },
  {
    "slug": "moulins",
    "name": "Déménagement"
  },
  {
    "slug": "mulhouse",
    "name": "professionnel à Agen"
  },
  {
    "slug": "nancy",
    "name": "Déménagement"
  },
  {
    "slug": "nanterre",
    "name": "Déménagement"
  },
  {
    "slug": "nantes",
    "name": "Déménagement"
  },
  {
    "slug": "nevers",
    "name": "Déménagement"
  },
  {
    "slug": "nice",
    "name": "Déménagement"
  },
  {
    "slug": "nimes",
    "name": "Déménagement"
  },
  {
    "slug": "niort",
    "name": "Déménagement"
  },
  {
    "slug": "orleans",
    "name": "Déménagement"
  },
  {
    "slug": "paris",
    "name": "Déménagement"
  },
  {
    "slug": "pau",
    "name": "Déménagement"
  },
  {
    "slug": "perigueux",
    "name": "Déménagement"
  },
  {
    "slug": "perpignan",
    "name": "Déménagement"
  },
  {
    "slug": "poitiers",
    "name": "Déménagement"
  },
  {
    "slug": "privas",
    "name": "Déménagement"
  },
  {
    "slug": "reims",
    "name": "professionnel à Agen"
  },
  {
    "slug": "rennes",
    "name": "Déménagement"
  },
  {
    "slug": "rodez",
    "name": "Déménagement"
  },
  {
    "slug": "rouen",
    "name": "Déménagement"
  },
  {
    "slug": "saint-brieuc",
    "name": "Déménagement"
  },
  {
    "slug": "saint-etienne",
    "name": "Déménagement"
  },
  {
    "slug": "saint-lo",
    "name": "Déménagement"
  },
  {
    "slug": "strasbourg",
    "name": "Déménagement"
  },
  {
    "slug": "tarbes",
    "name": "Déménagement"
  },
  {
    "slug": "toulon",
    "name": "Déménagement"
  },
  {
    "slug": "toulouse",
    "name": "Déménagement"
  },
  {
    "slug": "tours",
    "name": "Déménagement"
  },
  {
    "slug": "troyes",
    "name": "Déménagement"
  },
  {
    "slug": "tulle",
    "name": "Déménagement"
  },
  {
    "slug": "valence",
    "name": "Déménagement"
  },
  {
    "slug": "vannes",
    "name": "Déménagement"
  },
  {
    "slug": "versailles",
    "name": "Déménagement"
  },
  {
    "slug": "vesoul",
    "name": "Déménagement"
  }
]